flask_restplus_udata/__about__.py
flask_restplus_udata/__init__.py
flask_restplus_udata/_http.py
flask_restplus_udata/api.py
flask_restplus_udata/apidoc.py
flask_restplus_udata/cors.py
flask_restplus_udata/errors.py
flask_restplus_udata/fields.py
flask_restplus_udata/inputs.py
flask_restplus_udata/marshalling.py
flask_restplus_udata/mask.py
flask_restplus_udata/model.py
flask_restplus_udata/namespace.py
flask_restplus_udata/postman.py
flask_restplus_udata/representations.py
flask_restplus_udata/reqparse.py
flask_restplus_udata/resource.py
flask_restplus_udata/swagger.py
flask_restplus_udata/utils.py
flask_restplus_udata/schemas/__init__.py
flask_restplus_udata/schemas/oas-2.0.json
flask_restplus_udata/static/droid-sans.css
flask_restplus_udata/static/favicon-16x16.png
flask_restplus_udata/static/favicon-32x32.png
flask_restplus_udata/static/oauth2-redirect.html
flask_restplus_udata/static/swagger-ui-bundle.js
flask_restplus_udata/static/swagger-ui-bundle.js.map
flask_restplus_udata/static/swagger-ui-es-bundle-core.js
flask_restplus_udata/static/swagger-ui-es-bundle-core.js.map
flask_restplus_udata/static/swagger-ui-es-bundle.js
flask_restplus_udata/static/swagger-ui-es-bundle.js.map
flask_restplus_udata/static/swagger-ui-standalone-preset.js
flask_restplus_udata/static/swagger-ui-standalone-preset.js.map
flask_restplus_udata/static/swagger-ui.css
flask_restplus_udata/static/swagger-ui.css.map
flask_restplus_udata/static/swagger-ui.js
flask_restplus_udata/static/swagger-ui.js.map
flask_restplus_udata/static/files/.npmignore
flask_restplus_udata/static/files/droid-sans-latin-400.woff
flask_restplus_udata/static/files/droid-sans-latin-400.woff2
flask_restplus_udata/static/files/droid-sans-latin-700.woff
flask_restplus_udata/static/files/droid-sans-latin-700.woff2
flask_restplus_udata/templates/swagger-ui-css.html
flask_restplus_udata/templates/swagger-ui-libs.html
flask_restplus_udata/templates/swagger-ui.html
flask_restplus_udata-0.17.0.dist-info/AUTHORS.rst
flask_restplus_udata-0.17.0.dist-info/LICENSE
flask_restplus_udata-0.17.0.dist-info/METADATA
flask_restplus_udata-0.17.0.dist-info/WHEEL
flask_restplus_udata-0.17.0.dist-info/top_level.txt
flask_restplus_udata-0.17.0.dist-info/RECORD
