Metadata-Version: 2.1
Name: flask-restplus-udata
Version: 0.17.0
Summary: Temporary fork for update
Home-page: https://github.com/quaxsze/flask_restplus_udata
Author: quaxzse
License: BSD-3-Clause
Keywords: flask restplus rest api swagger openapi
Platform: UNKNOWN
Classifier: Development Status :: 3 - Alpha
Classifier: Programming Language :: Python
Classifier: Environment :: Web Environment
Classifier: Operating System :: OS Independent
Classifier: Intended Audience :: Developers
Classifier: Topic :: System :: Software Distribution
Classifier: Programming Language :: Python
Classifier: Programming Language :: Python :: 2
Classifier: Programming Language :: Python :: 2.7
Classifier: Programming Language :: Python :: 3
Classifier: Programming Language :: Python :: 3.4
Classifier: Programming Language :: Python :: 3.5
Classifier: Programming Language :: Python :: 3.6
Classifier: Programming Language :: Python :: 3.7
Classifier: Programming Language :: Python :: Implementation :: PyPy
Classifier: Topic :: Software Development :: Libraries :: Python Modules
Classifier: License :: OSI Approved :: BSD License
License-File: LICENSE
License-File: AUTHORS.rst
Requires-Dist: aniso8601 (>=0.82)
Requires-Dist: jsonschema
Requires-Dist: Flask (>=0.8)
Requires-Dist: pytz
Requires-Dist: six (>=1.3.0)
Requires-Dist: enum34 ; python_version < "3.4"
Provides-Extra: dev
Requires-Dist: blinker ; extra == 'dev'
Requires-Dist: Faker (==2.0.0) ; extra == 'dev'
Requires-Dist: mock (==3.0.5) ; extra == 'dev'
Requires-Dist: pytest-benchmark (==3.2.2) ; extra == 'dev'
Requires-Dist: pytest-cov (==2.7.1) ; extra == 'dev'
Requires-Dist: pytest-flask (==0.15.0) ; extra == 'dev'
Requires-Dist: pytest-mock (==1.10.4) ; extra == 'dev'
Requires-Dist: pytest-profiling (==1.7.0) ; extra == 'dev'
Requires-Dist: pytest-sugar (==0.9.2) ; extra == 'dev'
Requires-Dist: tzlocal ; extra == 'dev'
Requires-Dist: invoke (==1.3.0) ; extra == 'dev'
Requires-Dist: flake8 (==3.7.8) ; extra == 'dev'
Requires-Dist: readme-renderer (==24.0) ; extra == 'dev'
Requires-Dist: tox (==3.13.2) ; extra == 'dev'
Requires-Dist: pytest (==4.6.5) ; (python_version < "3.5") and extra == 'dev'
Requires-Dist: pytest (==5.0.1) ; (python_version >= "3.5") and extra == 'dev'
Provides-Extra: doc
Requires-Dist: alabaster (==0.7.12) ; extra == 'doc'
Requires-Dist: Sphinx (==2.1.2) ; extra == 'doc'
Requires-Dist: sphinx-issues (==1.2.0) ; extra == 'doc'
Provides-Extra: test
Requires-Dist: blinker ; extra == 'test'
Requires-Dist: Faker (==2.0.0) ; extra == 'test'
Requires-Dist: mock (==3.0.5) ; extra == 'test'
Requires-Dist: pytest-benchmark (==3.2.2) ; extra == 'test'
Requires-Dist: pytest-cov (==2.7.1) ; extra == 'test'
Requires-Dist: pytest-flask (==0.15.0) ; extra == 'test'
Requires-Dist: pytest-mock (==1.10.4) ; extra == 'test'
Requires-Dist: pytest-profiling (==1.7.0) ; extra == 'test'
Requires-Dist: pytest-sugar (==0.9.2) ; extra == 'test'
Requires-Dist: tzlocal ; extra == 'test'
Requires-Dist: pytest (==4.6.5) ; (python_version < "3.5") and extra == 'test'
Requires-Dist: pytest (==5.0.1) ; (python_version >= "3.5") and extra == 'test'
